seamm_jobserver/__init__.py
seamm_jobserver/_version.py
seamm_jobserver/jobserver.py
seamm_jobserver-2025.11.13.dist-info/licenses/AUTHORS.rst
seamm_jobserver-2025.11.13.dist-info/licenses/LICENSE
seamm_jobserver-2025.11.13.dist-info/METADATA
seamm_jobserver-2025.11.13.dist-info/WHEEL
seamm_jobserver-2025.11.13.dist-info/entry_points.txt
seamm_jobserver-2025.11.13.dist-info/top_level.txt
seamm_jobserver-2025.11.13.dist-info/RECORD
