Metadata-Version: 2.4
Name: seamm_jobserver
Version: 2025.11.13
Summary: The JobServer for the SEAMM environment.
Home-page: https://github.com/molssi-seam/seamm_jobserver
Author: Paul Saxe
Author-email: psaxe@molssi.org
License: LGPLv3+
Keywords: seamm_jobserver
Platform: Linux
Platform: Mac OS-X
Platform: Unix
Platform: Windows
Classifier: Development Status :: 2 - Pre-Alpha
Classifier: Intended Audience :: Science/Research
Classifier: License :: OSI Approved :: GNU Lesser General Public License v3 or later (LGPLv3+)
Classifier: Natural Language :: English
Classifier: Programming Language :: Python :: 3 :: Only
Classifier: Programming Language :: Python :: 3.8
Classifier: Programming Language :: Python :: 3.9
Classifier: Topic :: Scientific/Engineering
Classifier: Topic :: Scientific/Engineering :: Chemistry
License-File: LICENSE
License-File: AUTHORS.rst
Requires-Dist: seamm
Requires-Dist: psutil
Dynamic: author
Dynamic: author-email
Dynamic: classifier
Dynamic: description
Dynamic: description-content-type
Dynamic: home-page
Dynamic: keywords
Dynamic: license
Dynamic: license-file
Dynamic: platform
Dynamic: requires-dist
Dynamic: summary
